nlptranslatetk/__init__.py
nlptranslatetk/constants.py
nlptranslatetk/convert_str.py
nlptranslatetk/language_id.py
nlptranslatetk/objects.py
nlptranslatetk/util.py
nlptranslatetk-1.0.0.dist-info/WHEEL
nlptranslatetk-1.0.0.dist-info/METADATA
nlptranslatetk-1.0.0.dist-info/RECORD
